sveltish/__init__.py
sveltish/_modidx.py
sveltish/signals.py
sveltish/stores.py
sveltish/utils.py
sveltish-1.2.9.dist-info/LICENSE
sveltish-1.2.9.dist-info/METADATA
sveltish-1.2.9.dist-info/WHEEL
sveltish-1.2.9.dist-info/entry_points.txt
sveltish-1.2.9.dist-info/top_level.txt
sveltish-1.2.9.dist-info/RECORD
