Metadata-Version: 2.1
Name: sveltish
Version: 1.2.9
Summary: A Svelte Stores implementation in Python.
Home-page: https://github.com/fredguth/sveltish
Author: Fred Guth
Author-email: fredguth@fredguth.com
License: Apache Software License 2.0
Keywords: nbdev jupyter notebook python
Classifier: Development Status :: 4 - Beta
Classifier: Intended Audience :: Developers
Classifier: Natural Language :: English
Classifier: Programming Language :: Python :: 3.7
Classifier: Programming Language :: Python :: 3.8
Classifier: Programming Language :: Python :: 3.9
Classifier: Programming Language :: Python :: 3.10
Classifier: License :: OSI Approved :: Apache Software License
Requires-Python: >=3.7
License-File: LICENSE
Requires-Dist: fastcore
Requires-Dist: typing
Requires-Dist: typing-extensions
Provides-Extra: dev
